[
  {
    "team": "Duke",
    "region": "East",
    "seed": 1,
    "elo": 2089.303,
    "conference": "ACC",
    "homeCourt": 83.04591,
    "distances": {
      "University of Dayton Arena, Dayton, Ohio": 385.79,
      "Amica Mutual Pavilion, Providence, Rhode Island": 570.42,
      "Rupp Arena, Lexington, Kentucky": 338.17,
      "Intrust Bank Arena, Wichita, Kansas": 1024.04,
      "Ball Arena, Denver, Colorado": 1442.81,
      "Rocket Mortgage FieldHouse, Cleveland, Ohio": 407.03,
      "Fiserv Forum, Milwaukee, Wisconsin": 681.9,
      "PNC Arena, Raleigh, North Carolina": 18.43,
      "Climate Pledge Arena, Seattle, Washington": 2345.01,
      "Prudential Center, Newark, New Jersey": 416.72,
      "State Farm Arena, Atlanta, Georgia": 346.09,
      "Lucas Oil Stadium, Indianapolis, Indiana": 471.95,
      "Chase Center, San Francisco, California": 2387.81,
      "Alamodome, San Antonio, Texas": 1222.35
    }
  },
  {
    "team": "Houston",
    "region": "Midwest",
    "seed": 1,
    "elo": 2074.552,
    "conference": "Big 12",
    "homeCourt": 84.47469,
    "distances": {
      "University of Dayton Arena, Dayton, Ohio": 934.77,
      "Amica Mutual Pavilion, Providence, Rhode Island": 1573.35,
      "Rupp Arena, Lexington, Kentucky": 845.25,
      "Intrust Bank Arena, Wichita, Kansas": 557.71,
      "Ball Arena, Denver, Colorado": 879.14,
      "Rocket Mortgage FieldHouse, Cleveland, Ohio": 1114.21,
      "Fiserv Forum, Milwaukee, Wisconsin": 1004.77,
      "PNC Arena, Raleigh, North Carolina": 1052.86,
      "Climate Pledge Arena, Seattle, Washington": 1892.17,
      "Prudential Center, Newark, New Jersey": 1411.69,
      "State Farm Arena, Atlanta, Georgia": 701.66,
      "Lucas Oil Stadium, Indianapolis, Indiana": 864.55,
      "Chase Center, San Francisco, California": 1643.33,
      "Alamodome, San Antonio, Texas": 188.76
    }
  },
  {
    "team": "Auburn",
    "region": "West",
    "seed": 1,
    "elo": 2049.707,
    "conference": "SEC",
    "homeCourt": 67.584,
    "distances": {
      "University of Dayton Arena, Dayton, Ohio": 496.48,
      "Amica Mutual Pavilion, Providence, Rhode Island": 1000.3,
      "Rupp Arena, Lexington, Kentucky": 379.04,
      "Intrust Bank Arena, Wichita, Kansas": 755.89,
      "Ball Arena, Denver, Colorado": 1193.98,
      "Rocket Mortgage FieldHouse, Cleveland, Ohio": 647.49,
      "Fiserv Forum, Milwaukee, Wisconsin": 731.84,
      "PNC Arena, Raleigh, North Carolina": 445.1,
      "Climate Pledge Arena, Seattle, Washington": 2182.55,
      "Prudential Center, Newark, New Jersey": 840.37,
      "State Farm Arena, Atlanta, Georgia": 101.01,
      "Lucas Oil Stadium, Indianapolis, Indiana": 494.4,
      "Chase Center, San Francisco, California": 2104.83,
      "Alamodome, San Antonio, Texas": 801.38
    }
  },
  {
    "team": "Florida",
    "region": "South",
    "seed": 1,
    "elo": 2040.319,
    "conference": "SEC",
    "homeCourt": 62.82391,
    "distances": {
      "University of Dayton Arena, Dayton, Ohio": 703.18,
      "Amica Mutual Pavilion, Providence, Rhode Island": 1037.33,
      "Rupp Arena, Lexington, Kentucky": 592.11,
      "Intrust Bank Arena, Wichita, Kansas": 1024.76,
      "Ball Arena, Denver, Colorado": 1460.89,
      "Rocket Mortgage FieldHouse, Cleveland, Ohio": 817.39,
      "Fiserv Forum, Milwaukee, Wisconsin": 974.12,
      "PNC Arena, Raleigh, North Carolina": 472.9,
      "Climate Pledge Arena, Seattle, Washington": 2457.05,
      "Prudential Center, Newark, New Jersey": 891.49,
      "State Farm Arena, Atlanta, Georgia": 308.03,
      "Lucas Oil Stadium, Indianapolis, Indiana": 729.97,
      "Chase Center, San Francisco, California": 2355.43,
      "Alamodome, San Antonio, Texas": 972.32
    }
  },
  {
    "team": "Alabama",
    "region": "West",
    "seed": 2,
    "elo": 2031.764,
    "conference": "SEC",
    "homeCourt": 100.502,
    "distances": {
      "University of Dayton Arena, Dayton, Ohio": 487.39,
      "Amica Mutual Pavilion, Providence, Rhode Island": 1064.83,
      "Rupp Arena, Lexington, Kentucky": 375.57,
      "Intrust Bank Arena, Wichita, Kansas": 630.82,
      "Ball Arena, Denver, Colorado": 1068.23,
      "Rocket Mortgage FieldHouse, Cleveland, Ohio": 656.38,
      "Fiserv Forum, Milwaukee, Wisconsin": 678.64,
      "PNC Arena, Raleigh, North Carolina": 535.23,
      "Climate Pledge Arena, Seattle, Washington": 2062.46,
      "Prudential Center, Newark, New Jersey": 903.09,
      "State Farm Arena, Atlanta, Georgia": 186.98,
      "Lucas Oil Stadium, Indianapolis, Indiana": 458.3,
      "Chase Center, San Francisco, California": 1976.7,
      "Alamodome, San Antonio, Texas": 695.81
    }
  },
  {
    "team": "Michigan St.",
    "region": "East",
    "seed": 2,
    "elo": 2009.002,
    "conference": "Big Ten",
    "homeCourt": 81.57139,
    "distances": {
      "University of Dayton Arena, Dayton, Ohio": 207.27,
      "Amica Mutual Pavilion, Providence, Rhode Island": 671.36,
      "Rupp Arena, Lexington, Kentucky": 323.1,
      "Intrust Bank Arena, Wichita, Kansas": 763.14,
      "Ball Arena, Denver, Colorado": 1086.44,
      "Rocket Mortgage FieldHouse, Cleveland, Ohio": 166.51,
      "Fiserv Forum, Milwaukee, Wisconsin": 176.2,
      "PNC Arena, Raleigh, North Carolina": 568.47,
      "Climate Pledge Arena, Seattle, Washington": 1861.55,
      "Prudential Center, Newark, New Jersey": 549.7,
      "State Farm Arena, Atlanta, Georgia": 619.03,
      "Lucas Oil Stadium, Indianapolis, Indiana": 223.27,
      "Chase Center, San Francisco, California": 2016.16,
      "Alamodome, San Antonio, Texas": 1203.83
    }
  },
  {
    "team": "St. John's",
    "region": "Midwest",
    "seed": 2,
    "elo": 1987.206,
    "conference": "Big East",
    "homeCourt": 43.39108,
    "distances": {
      "University of Dayton Arena, Dayton, Ohio": 553.34,
      "Amica Mutual Pavilion, Providence, Rhode Island": 146.61,
      "Rupp Arena, Lexington, Kentucky": 600.63,
      "Intrust Bank Arena, Wichita, Kansas": 1275.89,
      "Ball Arena, Denver, Colorado": 1642.69,
      "Rocket Mortgage FieldHouse, Cleveland, Ohio": 414.9,
      "Fiserv Forum, Milwaukee, Wisconsin": 744.64,
      "PNC Arena, Raleigh, North Carolina": 430.53,
      "Climate Pledge Arena, Seattle, Washington": 2418.7,
      "Prudential Center, Newark, New Jersey": 19.22,
      "State Farm Arena, Atlanta, Georgia": 754.09,
      "Lucas Oil Stadium, Indianapolis, Indiana": 656.1,
      "Chase Center, San Francisco, California": 2580.84,
      "Alamodome, San Antonio, Texas": 1592.12
    }
  },
  {
    "team": "Tennessee",
    "region": "South",
    "seed": 2,
    "elo": 1977.244,
    "conference": "SEC",
    "homeCourt": 86.19893,
    "distances": {
      "University of Dayton Arena, Dayton, Ohio": 260.81,
      "Amica Mutual Pavilion, Providence, Rhode Island": 784.85,
      "Rupp Arena, Lexington, Kentucky": 147.6,
      "Intrust Bank Arena, Wichita, Kansas": 752.23,
      "Ball Arena, Denver, Colorado": 1179.34,
      "Rocket Mortgage FieldHouse, Cleveland, Ohio": 400.44,
      "Fiserv Forum, Milwaukee, Wisconsin": 533.21,
      "PNC Arena, Raleigh, North Carolina": 291.88,
      "Climate Pledge Arena, Seattle, Washington": 2115.4,
      "Prudential Center, Newark, New Jersey": 623.01,
      "State Farm Arena, Atlanta, Georgia": 154.25,
      "Lucas Oil Stadium, Indianapolis, Indiana": 289.24,
      "Chase Center, San Francisco, California": 2119.95,
      "Alamodome, San Antonio, Texas": 959.21
    }
  },
  {
    "team": "Texas Tech",
    "region": "West",
    "seed": 3,
    "elo": 1952.853,
    "conference": "Big 12",
    "homeCourt": 80.30434,
    "distances": {
      "University of Dayton Arena, Dayton, Ohio": 1068.13,
      "Amica Mutual Pavilion, Providence, Rhode Island": 1753.02,
      "Rupp Arena, Lexington, Kentucky": 1022.2,
      "Intrust Bank Arena, Wichita, Kansas": 381.44,
      "Ball Arena, Denver, Colorado": 458.09,
      "Rocket Mortgage FieldHouse, Cleveland, Ohio": 1232.3,
      "Fiserv Forum, Milwaukee, Wisconsin": 998.67,
      "PNC Arena, Raleigh, North Carolina": 1325.17,
      "Climate Pledge Arena, Seattle, Washington": 1438.79,
      "Prudential Center, Newark, New Jersey": 1599.76,
      "State Farm Arena, Atlanta, Georgia": 1007.43,
      "Lucas Oil Stadium, Indianapolis, Indiana": 970.02,
      "Chase Center, San Francisco, California": 1185.15,
      "Alamodome, San Antonio, Texas": 351.49
    }
  },
  {
    "team": "Gonzaga",
    "region": "East",
    "seed": 3,
    "elo": 1952.656,
    "conference": "WCC",
    "homeCourt": 71.56569,
    "distances": {
      "University of Dayton Arena, Dayton, Ohio": 1735.42,
      "Amica Mutual Pavilion, Providence, Rhode Island": 2264.26,
      "Rupp Arena, Lexington, Kentucky": 1781.26,
      "Intrust Bank Arena, Wichita, Kansas": 1227.04,
      "Ball Arena, Denver, Colorado": 825.36,
      "Rocket Mortgage FieldHouse, Cleveland, Ohio": 1796.05,
      "Fiserv Forum, Milwaukee, Wisconsin": 1461.2,
      "PNC Arena, Raleigh, North Carolina": 2133.45,
      "Climate Pledge Arena, Seattle, Washington": 231.13,
      "Prudential Center, Newark, New Jersey": 2170.29,
      "State Farm Arena, Atlanta, Georgia": 1959.87,
      "Lucas Oil Stadium, Indianapolis, Indiana": 1643.63,
      "Chase Center, San Francisco, California": 728.48,
      "Alamodome, San Antonio, Texas": 1614.3
    }
  },
  {
    "team": "Louisville",
    "region": "Midwest",
    "seed": 3,
    "elo": 1950.435,
    "conference": "ACC",
    "homeCourt": 66.29934,
    "distances": {
      "University of Dayton Arena, Dayton, Ohio": 132.24,
      "Amica Mutual Pavilion, Providence, Rhode Island": 798.26,
      "Rupp Arena, Lexington, Kentucky": 69.91,
      "Intrust Bank Arena, Wichita, Kansas": 632.67,
      "Ball Arena, Denver, Colorado": 1039.15,
      "Rocket Mortgage FieldHouse, Cleveland, Ohio": 311.16,
      "Fiserv Forum, Milwaukee, Wisconsin": 349.45,
      "PNC Arena, Raleigh, North Carolina": 424.06,
      "Climate Pledge Arena, Seattle, Washington": 1944.24,
      "Prudential Center, Newark, New Jersey": 642.04,
      "State Farm Arena, Atlanta, Georgia": 319.3,
      "Lucas Oil Stadium, Indianapolis, Indiana": 106.06,
      "Chase Center, San Francisco, California": 1985.78,
      "Alamodome, San Antonio, Texas": 950.27
    }
  },
  {
    "team": "Maryland",
    "region": "South",
    "seed": 3,
    "elo": 1940.398,
    "conference": "Big Ten",
    "homeCourt": 74.57055,
    "distances": {
      "University of Dayton Arena, Dayton, Ohio": 392.32,
      "Amica Mutual Pavilion, Providence, Rhode Island": 350.92,
      "Rupp Arena, Lexington, Kentucky": 414.87,
      "Intrust Bank Arena, Wichita, Kansas": 1109.34,
      "Ball Arena, Denver, Colorado": 1497.95,
      "Rocket Mortgage FieldHouse, Cleveland, Ohio": 305.31,
      "Fiserv Forum, Milwaukee, Wisconsin": 638.11,
      "PNC Arena, Raleigh, North Carolina": 240.11,
      "Climate Pledge Arena, Seattle, Washington": 2330.41,
      "Prudential Center, Newark, New Jersey": 190.39,
      "State Farm Arena, Atlanta, Georgia": 549.85,
      "Lucas Oil Stadium, Indianapolis, Indiana": 496.75,
      "Chase Center, San Francisco, California": 2443.32,
      "Alamodome, San Antonio, Texas": 1393.73
    }
  },
  {
    "team": "Saint Mary's (CA)",
    "region": "East",
    "seed": 4,
    "elo": 1936.807,
    "conference": "WCC",
    "homeCourt": 51.3288,
    "distances": {
      "University of Dayton Arena, Dayton, Ohio": 2035.54,
      "Amica Mutual Pavilion, Providence, Rhode Island": 2671.13,
      "Rupp Arena, Lexington, Kentucky": 2039.75,
      "Intrust Bank Arena, Wichita, Kansas": 1352.66,
      "Ball Arena, Denver, Colorado": 931.07,
      "Rocket Mortgage FieldHouse, Cleveland, Ohio": 2150.11,
      "Fiserv Forum, Milwaukee, Wisconsin": 1824.71,
      "PNC Arena, Raleigh, North Carolina": 2387.73,
      "Climate Pledge Arena, Seattle, Washington": 675.26,
      "Prudential Center, Newark, New Jersey": 2545.67,
      "State Farm Arena, Atlanta, Georgia": 2122.38,
      "Lucas Oil Stadium, Indianapolis, Indiana": 1931.78,
      "Chase Center, San Francisco, California": 16.02,
      "Alamodome, San Antonio, Texas": 1475.54
    }
  },
  {
    "team": "Clemson",
    "region": "West",
    "seed": 4,
    "elo": 1916.291,
    "conference": "ACC",
    "homeCourt": 81.81437,
    "distances": {
      "University of Dayton Arena, Dayton, Ohio": 356.3,
      "Amica Mutual Pavilion, Providence, Rhode Island": 791.3,
      "Rupp Arena, Lexington, Kentucky": 249.87,
      "Intrust Bank Arena, Wichita, Kansas": 835.22,
      "Ball Arena, Denver, Colorado": 1267.9,
      "Rocket Mortgage FieldHouse, Cleveland, Ohio": 473.94,
      "Fiserv Forum, Milwaukee, Wisconsin": 638.14,
      "PNC Arena, Raleigh, North Carolina": 245.11,
      "Climate Pledge Arena, Seattle, Washington": 2216.14,
      "Prudential Center, Newark, New Jersey": 631.42,
      "State Farm Arena, Atlanta, Georgia": 109.84,
      "Lucas Oil Stadium, Indianapolis, Indiana": 395.02,
      "Chase Center, San Francisco, California": 2203.29,
      "Alamodome, San Antonio, Texas": 985.7
    }
  },
  {
    "team": "Kansas",
    "region": "South",
    "seed": 4,
    "elo": 1911.125,
    "conference": "Big 12",
    "homeCourt": 89.09142,
    "distances": {
      "University of Dayton Arena, Dayton, Ohio": 594.67,
      "Amica Mutual Pavilion, Providence, Rhode Island": 1269.32,
      "Rupp Arena, Lexington, Kentucky": 586.24,
      "Intrust Bank Arena, Wichita, Kansas": 142.52,
      "Ball Arena, Denver, Colorado": 524.52,
      "Rocket Mortgage FieldHouse, Cleveland, Ohio": 738.18,
      "Fiserv Forum, Milwaukee, Wisconsin": 476.34,
      "PNC Arena, Raleigh, North Carolina": 934.44,
      "Climate Pledge Arena, Seattle, Washington": 1481.57,
      "Prudential Center, Newark, New Jersey": 1125.68,
      "State Farm Arena, Atlanta, Georgia": 703.3,
      "Lucas Oil Stadium, Indianapolis, Indiana": 490.26,
      "Chase Center, San Francisco, California": 1469.91,
      "Alamodome, San Antonio, Texas": 682.51
    }
  },
  {
    "team": "Arizona",
    "region": "Midwest",
    "seed": 4,
    "elo": 1906.818,
    "conference": "Big 12",
    "homeCourt": 83.74467,
    "distances": {
      "University of Dayton Arena, Dayton, Ohio": 1580.2,
      "Amica Mutual Pavilion, Providence, Rhode Island": 2262.97,
      "Rupp Arena, Lexington, Kentucky": 1546.12,
      "Intrust Bank Arena, Wichita, Kansas": 859.77,
      "Ball Arena, Denver, Colorado": 616.92,
      "Rocket Mortgage FieldHouse, Cleveland, Ohio": 1733.76,
      "Fiserv Forum, Milwaukee, Wisconsin": 1461.14,
      "PNC Arena, Raleigh, North Carolina": 1859.13,
      "Climate Pledge Arena, Seattle, Washington": 1219.34,
      "Prudential Center, Newark, New Jersey": 2114.66,
      "State Farm Arena, Atlanta, Georgia": 1542.92,
      "Lucas Oil Stadium, Indianapolis, Indiana": 1478.13,
      "Chase Center, San Francisco, California": 750.98,
      "Alamodome, San Antonio, Texas": 767.16
    }
  },
  {
    "team": "UConn",
    "region": "West",
    "seed": 5,
    "elo": 1899.5,
    "conference": "Big East",
    "homeCourt": 54.18959,
    "distances": {
      "University of Dayton Arena, Dayton, Ohio": 642.52,
      "Amica Mutual Pavilion, Providence, Rhode Island": 42.88,
      "Rupp Arena, Lexington, Kentucky": 699.89,
      "Intrust Bank Arena, Wichita, Kansas": 1360.69,
      "Ball Arena, Denver, Colorado": 1713.76,
      "Rocket Mortgage FieldHouse, Cleveland, Ohio": 488.85,
      "Fiserv Forum, Milwaukee, Wisconsin": 804.56,
      "PNC Arena, Raleigh, North Carolina": 541.69,
      "Climate Pledge Arena, Seattle, Washington": 2455.43,
      "Prudential Center, Newark, New Jersey": 124.69,
      "State Farm Arena, Atlanta, Georgia": 864.86,
      "Lucas Oil Stadium, Indianapolis, Indiana": 742.58,
      "Chase Center, San Francisco, California": 2645.25,
      "Alamodome, San Antonio, Texas": 1695.88
    }
  },
  {
    "team": "Iowa St.",
    "region": "East",
    "seed": 5,
    "elo": 1895.161,
    "conference": "Big 12",
    "homeCourt": 77.82376,
    "distances": {
      "University of Dayton Arena, Dayton, Ohio": 519.0,
      "Amica Mutual Pavilion, Providence, Rhode Island": 1142.43,
      "Rupp Arena, Lexington, Kentucky": 556.7,
      "Intrust Bank Arena, Wichita, Kansas": 358.08,
      "Ball Arena, Denver, Colorado": 614.95,
      "Rocket Mortgage FieldHouse, Cleveland, Ohio": 618.38,
      "Fiserv Forum, Milwaukee, Wisconsin": 300.6,
      "PNC Arena, Raleigh, North Carolina": 909.82,
      "Climate Pledge Arena, Seattle, Washington": 1453.45,
      "Prudential Center, Newark, New Jersey": 1013.91,
      "State Farm Arena, Atlanta, Georgia": 761.2,
      "Lucas Oil Stadium, Indianapolis, Indiana": 421.66,
      "Chase Center, San Francisco, California": 1547.78,
      "Alamodome, San Antonio, Texas": 910.52
    }
  },
  {
    "team": "Texas A&M",
    "region": "South",
    "seed": 5,
    "elo": 1892.981,
    "conference": "SEC",
    "homeCourt": 66.2533,
    "distances": {
      "University of Dayton Arena, Dayton, Ohio": 930.46,
      "Amica Mutual Pavilion, Providence, Rhode Island": 1584.73,
      "Rupp Arena, Lexington, Kentucky": 848.5,
      "Intrust Bank Arena, Wichita, Kansas": 490.69,
      "Ball Arena, Denver, Colorado": 797.12,
      "Rocket Mortgage FieldHouse, Cleveland, Ohio": 1109.4,
      "Fiserv Forum, Milwaukee, Wisconsin": 975.36,
      "PNC Arena, Raleigh, North Carolina": 1080.34,
      "Climate Pledge Arena, Seattle, Washington": 1809.14,
      "Prudential Center, Newark, New Jersey": 1423.76,
      "State Farm Arena, Atlanta, Georgia": 732.83,
      "Lucas Oil Stadium, Indianapolis, Indiana": 853.32,
      "Chase Center, San Francisco, California": 1564.61,
      "Alamodome, San Antonio, Texas": 151.71
    }
  },
  {
    "team": "BYU",
    "region": "Midwest",
    "seed": 5,
    "elo": 1884.394,
    "conference": "Big 12",
    "homeCourt": 98.47079,
    "distances": {
      "University of Dayton Arena, Dayton, Ohio": 1451.22,
      "Amica Mutual Pavilion, Providence, Rhode Island": 2085.51,
      "Rupp Arena, Lexington, Kentucky": 1460.3,
      "Intrust Bank Arena, Wichita, Kansas": 790.2,
      "Ball Arena, Denver, Colorado": 354.07,
      "Rocket Mortgage FieldHouse, Cleveland, Ohio": 1563.75,
      "Fiserv Forum, Milwaukee, Wisconsin": 1239.15,
      "PNC Arena, Raleigh, North Carolina": 1811.72,
      "Climate Pledge Arena, Seattle, Washington": 736.18,
      "Prudential Center, Newark, New Jersey": 1959.32,
      "State Farm Arena, Atlanta, Georgia": 1565.32,
      "Lucas Oil Stadium, Indianapolis, Indiana": 1347.93,
      "Chase Center, San Francisco, California": 602.37,
      "Alamodome, San Antonio, Texas": 1055.31
    }
  },
  {
    "team": "Wisconsin",
    "region": "East",
    "seed": 6,
    "elo": 1863.745,
    "conference": "Big Ten",
    "homeCourt": 76.58871,
    "distances": {
      "University of Dayton Arena, Dayton, Ohio": 354.35,
      "Amica Mutual Pavilion, Providence, Rhode Island": 920.63,
      "Rupp Arena, Lexington, Kentucky": 431.36,
      "Intrust Bank Arena, Wichita, Kansas": 560.13,
      "Ball Arena, Denver, Colorado": 842.1,
      "Rocket Mortgage FieldHouse, Cleveland, Ohio": 408.97,
      "Fiserv Forum, Milwaukee, Wisconsin": 74.25,
      "PNC Arena, Raleigh, North Carolina": 758.42,
      "Climate Pledge Arena, Seattle, Washington": 1623.07,
      "Prudential Center, Newark, New Jersey": 799.62,
      "State Farm Arena, Atlanta, Georgia": 696.99,
      "Lucas Oil Stadium, Indianapolis, Indiana": 283.39,
      "Chase Center, San Francisco, California": 1766.48,
      "Alamodome, San Antonio, Texas": 1068.4
    }
  },
  {
    "team": "UCLA",
    "region": "Midwest",
    "seed": 6,
    "elo": 1863.713,
    "conference": "Big Ten",
    "homeCourt": 77.12961,
    "distances": {
      "University of Dayton Arena, Dayton, Ohio": 1924.14,
      "Amica Mutual Pavilion, Providence, Rhode Island": 2590.31,
      "Rupp Arena, Lexington, Kentucky": 1909.27,
      "Intrust Bank Arena, Wichita, Kansas": 1207.92,
      "Ball Arena, Denver, Colorado": 839.63,
      "Rocket Mortgage FieldHouse, Cleveland, Ohio": 2059.45,
      "Fiserv Forum, Milwaukee, Wisconsin": 1753.68,
      "PNC Arena, Raleigh, North Carolina": 2242.76,
      "Climate Pledge Arena, Seattle, Washington": 956.89,
      "Prudential Center, Newark, New Jersey": 2452.33,
      "State Farm Arena, Atlanta, Georgia": 1947.58,
      "Lucas Oil Stadium, Indianapolis, Indiana": 1819.63,
      "Chase Center, San Francisco, California": 337.28,
      "Alamodome, San Antonio, Texas": 1216.34
    }
  },
  {
    "team": "Illinois",
    "region": "South",
    "seed": 6,
    "elo": 1861.005,
    "conference": "Big Ten",
    "homeCourt": 71.86468,
    "distances": {
      "University of Dayton Arena, Dayton, Ohio": 215.05,
      "Amica Mutual Pavilion, Providence, Rhode Island": 886.0,
      "Rupp Arena, Lexington, Kentucky": 244.08,
      "Intrust Bank Arena, Wichita, Kansas": 517.82,
      "Ball Arena, Denver, Colorado": 890.69,
      "Rocket Mortgage FieldHouse, Cleveland, Ohio": 356.37,
      "Fiserv Forum, Milwaukee, Wisconsin": 205.5,
      "PNC Arena, Raleigh, North Carolina": 596.32,
      "Climate Pledge Arena, Seattle, Washington": 1766.87,
      "Prudential Center, Newark, New Jersey": 741.8,
      "State Farm Arena, Atlanta, Georgia": 484.39,
      "Lucas Oil Stadium, Indianapolis, Indiana": 111.57,
      "Chase Center, San Francisco, California": 1836.54,
      "Alamodome, San Antonio, Texas": 936.85
    }
  },
  {
    "team": "Ole Miss",
    "region": "West",
    "seed": 6,
    "elo": 1857.475,
    "conference": "SEC",
    "homeCourt": 73.00755,
    "distances": {
      "University of Dayton Arena, Dayton, Ohio": 473.38,
      "Amica Mutual Pavilion, Providence, Rhode Island": 1110.53,
      "Rupp Arena, Lexington, Kentucky": 379.06,
      "Intrust Bank Arena, Wichita, Kansas": 492.54,
      "Ball Arena, Denver, Colorado": 930.37,
      "Rocket Mortgage FieldHouse, Cleveland, Ohio": 652.02,
      "Fiserv Forum, Milwaukee, Wisconsin": 605.11,
      "PNC Arena, Raleigh, North Carolina": 620.63,
      "Climate Pledge Arena, Seattle, Washington": 1924.13,
      "Prudential Center, Newark, New Jersey": 949.43,
      "State Farm Arena, Atlanta, Georgia": 297.96,
      "Lucas Oil Stadium, Indianapolis, Indiana": 416.07,
      "Chase Center, San Francisco, California": 1844.14,
      "Alamodome, San Antonio, Texas": 625.96
    }
  },
  {
    "team": "VCU",
    "region": "West",
    "seed": 7,
    "elo": 1857.215,
    "conference": "A-10",
    "homeCourt": 71.68198,
    "distances": {
      "University of Dayton Arena, Dayton, Ohio": 394.81,
      "Amica Mutual Pavilion, Providence, Rhode Island": 436.37,
      "Rupp Arena, Lexington, Kentucky": 387.19,
      "Intrust Bank Arena, Wichita, Kansas": 1088.51,
      "Ball Arena, Denver, Colorado": 1492.27,
      "Rocket Mortgage FieldHouse, Cleveland, Ohio": 354.11,
      "Fiserv Forum, Milwaukee, Wisconsin": 669.66,
      "PNC Arena, Raleigh, North Carolina": 139.28,
      "Climate Pledge Arena, Seattle, Washington": 2356.95,
      "Prudential Center, Newark, New Jersey": 281.83,
      "State Farm Arena, Atlanta, Georgia": 469.71,
      "Lucas Oil Stadium, Indianapolis, Indiana": 494.97,
      "Chase Center, San Francisco, California": 2439.3,
      "Alamodome, San Antonio, Texas": 1333.19
    }
  },
  {
    "team": "Drake",
    "region": "East",
    "seed": 7,
    "elo": 1854.651,
    "conference": "MVC",
    "homeCourt": 59.36783,
    "distances": {
      "University of Dayton Arena, Dayton, Ohio": 512.93,
      "Amica Mutual Pavilion, Providence, Rhode Island": 1146.8,
      "Rupp Arena, Lexington, Kentucky": 544.73,
      "Intrust Bank Arena, Wichita, Kansas": 333.96,
      "Ball Arena, Denver, Colorado": 609.47,
      "Rocket Mortgage FieldHouse, Cleveland, Ohio": 619.93,
      "Fiserv Forum, Milwaukee, Wisconsin": 310.2,
      "PNC Arena, Raleigh, North Carolina": 899.16,
      "Climate Pledge Arena, Seattle, Washington": 1465.69,
      "Prudential Center, Newark, New Jersey": 1015.63,
      "State Farm Arena, Atlanta, Georgia": 740.95,
      "Lucas Oil Stadium, Indianapolis, Indiana": 413.42,
      "Chase Center, San Francisco, California": 1546.82,
      "Alamodome, San Antonio, Texas": 882.64
    }
  },
  {
    "team": "Marquette",
    "region": "South",
    "seed": 7,
    "elo": 1851.853,
    "conference": "Big East",
    "homeCourt": 67.61778,
    "distances": {
      "University of Dayton Arena, Dayton, Ohio": 298.47,
      "Amica Mutual Pavilion, Providence, Rhode Island": 846.0,
      "Rupp Arena, Lexington, Kentucky": 388.07,
      "Intrust Bank Arena, Wichita, Kansas": 618.94,
      "Ball Arena, Denver, Colorado": 915.3,
      "Rocket Mortgage FieldHouse, Cleveland, Ohio": 336.08,
      "Fiserv Forum, Milwaukee, Wisconsin": 0.61,
      "PNC Arena, Raleigh, North Carolina": 699.71,
      "Climate Pledge Arena, Seattle, Washington": 1692.88,
      "Prudential Center, Newark, New Jersey": 725.25,
      "State Farm Arena, Atlanta, Georgia": 667.79,
      "Lucas Oil Stadium, Indianapolis, Indiana": 243.8,
      "Chase Center, San Francisco, California": 1841.13,
      "Alamodome, San Antonio, Texas": 1107.31
    }
  },
  {
    "team": "Kentucky",
    "region": "Midwest",
    "seed": 7,
    "elo": 1851.058,
    "conference": "SEC",
    "homeCourt": 82.12686,
    "distances": {
      "University of Dayton Arena, Dayton, Ohio": 117.61,
      "Amica Mutual Pavilion, Providence, Rhode Island": 740.97,
      "Rupp Arena, Lexington, Kentucky": 0.36,
      "Intrust Bank Arena, Wichita, Kansas": 701.66,
      "Ball Arena, Denver, Colorado": 1109.38,
      "Rocket Mortgage FieldHouse, Cleveland, Ohio": 281.06,
      "Fiserv Forum, Milwaukee, Wisconsin": 388.98,
      "PNC Arena, Raleigh, North Carolina": 355.09,
      "Climate Pledge Arena, Seattle, Washington": 2010.4,
      "Prudential Center, Newark, New Jersey": 582.58,
      "State Farm Arena, Atlanta, Georgia": 295.76,
      "Lucas Oil Stadium, Indianapolis, Indiana": 148.41,
      "Chase Center, San Francisco, California": 2056.01,
      "Alamodome, San Antonio, Texas": 999.07
    }
  },
  {
    "team": "New Mexico",
    "region": "Midwest",
    "seed": 8,
    "elo": 1848.354,
    "conference": "MWC",
    "homeCourt": 89.07415,
    "distances": {
      "University of Dayton Arena, Dayton, Ohio": 1272.28,
      "Amica Mutual Pavilion, Providence, Rhode Island": 1952.02,
      "Rupp Arena, Lexington, Kentucky": 1245.72,
      "Intrust Bank Arena, Wichita, Kansas": 549.3,
      "Ball Arena, Denver, Colorado": 334.13,
      "Rocket Mortgage FieldHouse, Cleveland, Ohio": 1421.33,
      "Fiserv Forum, Milwaukee, Wisconsin": 1143.71,
      "PNC Arena, Raleigh, North Carolina": 1571.08,
      "Climate Pledge Arena, Seattle, Washington": 1185.19,
      "Prudential Center, Newark, New Jersey": 1806.18,
      "State Farm Arena, Atlanta, Georgia": 1271.84,
      "Lucas Oil Stadium, Indianapolis, Indiana": 1169.08,
      "Chase Center, San Francisco, California": 895.02,
      "Alamodome, San Antonio, Texas": 617.21
    }
  },
  {
    "team": "UC San Diego",
    "region": "East",
    "seed": 8,
    "elo": 1844.898,
    "conference": "Big West",
    "homeCourt": 59.54225,
    "distances": {
      "University of Dayton Arena, Dayton, Ohio": 1892.07,
      "Amica Mutual Pavilion, Providence, Rhode Island": 2565.78,
      "Rupp Arena, Lexington, Kentucky": 1870.23,
      "Intrust Bank Arena, Wichita, Kansas": 1170.46,
      "Ball Arena, Denver, Colorado": 831.79,
      "Rocket Mortgage FieldHouse, Cleveland, Ohio": 2034.09,
      "Fiserv Forum, Milwaukee, Wisconsin": 1737.69,
      "PNC Arena, Raleigh, North Carolina": 2196.51,
      "Climate Pledge Arena, Seattle, Washington": 1059.76,
      "Prudential Center, Newark, New Jersey": 2423.91,
      "State Farm Arena, Atlanta, Georgia": 1891.67,
      "Lucas Oil Stadium, Indianapolis, Indiana": 1788.03,
      "Chase Center, San Francisco, California": 452.6,
      "Alamodome, San Antonio, Texas": 1131.38
    }
  },
  {
    "team": "Baylor",
    "region": "South",
    "seed": 8,
    "elo": 1836.109,
    "conference": "Big 12",
    "homeCourt": 47.48352,
    "distances": {
      "University of Dayton Arena, Dayton, Ohio": 920.0,
      "Amica Mutual Pavilion, Providence, Rhode Island": 1586.4,
      "Rupp Arena, Lexington, Kentucky": 846.01,
      "Intrust Bank Arena, Wichita, Kansas": 422.97,
      "Ball Arena, Denver, Colorado": 717.11,
      "Rocket Mortgage FieldHouse, Cleveland, Ohio": 1097.32,
      "Fiserv Forum, Milwaukee, Wisconsin": 940.47,
      "PNC Arena, Raleigh, North Carolina": 1099.54,
      "Climate Pledge Arena, Seattle, Washington": 1729.63,
      "Prudential Center, Newark, New Jersey": 1426.58,
      "State Farm Arena, Atlanta, Georgia": 758.2,
      "Lucas Oil Stadium, Indianapolis, Indiana": 836.82,
      "Chase Center, San Francisco, California": 1494.87,
      "Alamodome, San Antonio, Texas": 166.98
    }
  },
  {
    "team": "Memphis",
    "region": "West",
    "seed": 8,
    "elo": 1834.618,
    "conference": "AAC",
    "homeCourt": 86.32083,
    "distances": {
      "University of Dayton Arena, Dayton, Ohio": 451.15,
      "Amica Mutual Pavilion, Providence, Rhode Island": 1107.18,
      "Rupp Arena, Lexington, Kentucky": 367.69,
      "Intrust Bank Arena, Wichita, Kansas": 441.68,
      "Ball Arena, Denver, Colorado": 880.08,
      "Rocket Mortgage FieldHouse, Cleveland, Ohio": 630.58,
      "Fiserv Forum, Milwaukee, Wisconsin": 556.79,
      "PNC Arena, Raleigh, North Carolina": 640.18,
      "Climate Pledge Arena, Seattle, Washington": 1868.07,
      "Prudential Center, Newark, New Jersey": 947.32,
      "State Farm Arena, Atlanta, Georgia": 336.75,
      "Lucas Oil Stadium, Indianapolis, Indiana": 383.18,
      "Chase Center, San Francisco, California": 1801.17,
      "Alamodome, San Antonio, Texas": 631.35
    }
  },
  {
    "team": "Purdue",
    "region": "West",
    "seed": 9,
    "elo": 1833.051,
    "conference": "Big Ten",
    "homeCourt": 109.2156,
    "distances": {
      "University of Dayton Arena, Dayton, Ohio": 152.23,
      "Amica Mutual Pavilion, Providence, Rhode Island": 813.77,
      "Rupp Arena, Lexington, Kentucky": 209.46,
      "Intrust Bank Arena, Wichita, Kansas": 590.42,
      "Ball Arena, Denver, Colorado": 957.63,
      "Rocket Mortgage FieldHouse, Cleveland, Ohio": 283.64,
      "Fiserv Forum, Milwaukee, Wisconsin": 187.6,
      "PNC Arena, Raleigh, North Carolina": 548.87,
      "Climate Pledge Arena, Seattle, Washington": 1815.81,
      "Prudential Center, Newark, New Jersey": 670.77,
      "State Farm Arena, Atlanta, Georgia": 480.84,
      "Lucas Oil Stadium, Indianapolis, Indiana": 61.45,
      "Chase Center, San Francisco, California": 1902.11,
      "Alamodome, San Antonio, Texas": 1001.42
    }
  },
  {
    "team": "Xavier",
    "region": "Midwest",
    "seed": 9,
    "elo": 1832.013,
    "conference": "Big East",
    "homeCourt": 84.81494,
    "distances": {
      "University of Dayton Arena, Dayton, Ohio": 42.83,
      "Amica Mutual Pavilion, Providence, Rhode Island": 711.14,
      "Rupp Arena, Lexington, Kentucky": 76.02,
      "Intrust Bank Arena, Wichita, Kansas": 704.61,
      "Ball Arena, Denver, Colorado": 1096.77,
      "Rocket Mortgage FieldHouse, Cleveland, Ohio": 218.55,
      "Fiserv Forum, Milwaukee, Wisconsin": 323.3,
      "PNC Arena, Raleigh, North Carolina": 391.2,
      "Climate Pledge Arena, Seattle, Washington": 1972.82,
      "Prudential Center, Newark, New Jersey": 557.41,
      "State Farm Arena, Atlanta, Georgia": 371.95,
      "Lucas Oil Stadium, Indianapolis, Indiana": 99.78,
      "Chase Center, San Francisco, California": 2043.58,
      "Alamodome, San Antonio, Texas": 1042.97
    }
  },
  {
    "team": "Arkansas",
    "region": "East",
    "seed": 9,
    "elo": 1828.403,
    "conference": "SEC",
    "homeCourt": 85.48567,
    "distances": {
      "University of Dayton Arena, Dayton, Ohio": 599.79,
      "Amica Mutual Pavilion, Providence, Rhode Island": 1283.32,
      "Rupp Arena, Lexington, Kentucky": 550.64,
      "Intrust Bank Arena, Wichita, Kansas": 208.36,
      "Ball Arena, Denver, Colorado": 644.55,
      "Rocket Mortgage FieldHouse, Cleveland, Ohio": 769.45,
      "Fiserv Forum, Milwaukee, Wisconsin": 585.35,
      "PNC Arena, Raleigh, North Carolina": 864.78,
      "Climate Pledge Arena, Seattle, Washington": 1646.27,
      "Prudential Center, Newark, New Jersey": 1128.81,
      "State Farm Arena, Atlanta, Georgia": 576.32,
      "Lucas Oil Stadium, Indianapolis, Indiana": 505.45,
      "Chase Center, San Francisco, California": 1561.6,
      "Alamodome, San Antonio, Texas": 522.4
    }
  },
  {
    "team": "Creighton",
    "region": "South",
    "seed": 9,
    "elo": 1827.128,
    "conference": "Big East",
    "homeCourt": 74.16709,
    "distances": {
      "University of Dayton Arena, Dayton, Ohio": 627.08,
      "Amica Mutual Pavilion, Providence, Rhode Island": 1267.89,
      "Rupp Arena, Lexington, Kentucky": 648.66,
      "Intrust Bank Arena, Wichita, Kansas": 258.02,
      "Ball Arena, Denver, Colorado": 488.39,
      "Rocket Mortgage FieldHouse, Cleveland, Ohio": 740.34,
      "Fiserv Forum, Milwaukee, Wisconsin": 429.96,
      "PNC Arena, Raleigh, North Carolina": 1004.09,
      "Climate Pledge Arena, Seattle, Washington": 1370.16,
      "Prudential Center, Newark, New Jersey": 1135.94,
      "State Farm Arena, Atlanta, Georgia": 817.65,
      "Lucas Oil Stadium, Indianapolis, Indiana": 525.19,
      "Chase Center, San Francisco, California": 1427.64,
      "Alamodome, San Antonio, Texas": 829.2
    }
  },
  {
    "team": "Colorado St.",
    "region": "West",
    "seed": 10,
    "elo": 1819.753,
    "conference": "MWC",
    "homeCourt": 60.36858,
    "distances": {
      "University of Dayton Arena, Dayton, Ohio": 1104.65,
      "Amica Mutual Pavilion, Providence, Rhode Island": 1745.72,
      "Rupp Arena, Lexington, Kentucky": 1114.07,
      "Intrust Bank Arena, Wichita, Kansas": 461.53,
      "Ball Arena, Denver, Colorado": 56.86,
      "Rocket Mortgage FieldHouse, Cleveland, Ohio": 1220.48,
      "Fiserv Forum, Milwaukee, Wisconsin": 901.09,
      "PNC Arena, Raleigh, North Carolina": 1466.42,
      "Climate Pledge Arena, Seattle, Washington": 984.39,
      "Prudential Center, Newark, New Jersey": 1616.19,
      "State Farm Arena, Atlanta, Georgia": 1230.91,
      "Lucas Oil Stadium, Indianapolis, Indiana": 1001.22,
      "Chase Center, San Francisco, California": 947.34,
      "Alamodome, San Antonio, Texas": 854.7
    }
  },
  {
    "team": "Georgia",
    "region": "Midwest",
    "seed": 10,
    "elo": 1815.588,
    "conference": "SEC",
    "homeCourt": 58.92334,
    "distances": {
      "University of Dayton Arena, Dayton, Ohio": 402.22,
      "Amica Mutual Pavilion, Providence, Rhode Island": 848.64,
      "Rupp Arena, Lexington, Kentucky": 290.27,
      "Intrust Bank Arena, Wichita, Kansas": 824.31,
      "Ball Arena, Denver, Colorado": 1260.38,
      "Rocket Mortgage FieldHouse, Cleveland, Ohio": 529.21,
      "Fiserv Forum, Milwaukee, Wisconsin": 674.31,
      "PNC Arena, Raleigh, North Carolina": 293.75,
      "Climate Pledge Arena, Seattle, Washington": 2221.95,
      "Prudential Center, Newark, New Jersey": 689.33,
      "State Farm Arena, Atlanta, Georgia": 60.19,
      "Lucas Oil Stadium, Indianapolis, Indiana": 429.94,
      "Chase Center, San Francisco, California": 2189.76,
      "Alamodome, San Antonio, Texas": 941.87
    }
  },
  {
    "team": "North Carolina",
    "region": "East",
    "seed": 10,
    "elo": 1814.202,
    "conference": "ACC",
    "homeCourt": 64.50067,
    "distances": {
      "University of Dayton Arena, Dayton, Ohio": 385.47,
      "Amica Mutual Pavilion, Providence, Rhode Island": 579.07,
      "Rupp Arena, Lexington, Kentucky": 335.32,
      "Intrust Bank Arena, Wichita, Kansas": 1019.19,
      "Ball Arena, Denver, Colorado": 1438.76,
      "Rocket Mortgage FieldHouse, Cleveland, Ohio": 410.53,
      "Fiserv Forum, Milwaukee, Wisconsin": 682.25,
      "PNC Arena, Raleigh, North Carolina": 20.21,
      "Climate Pledge Arena, Seattle, Washington": 2343.15,
      "Prudential Center, Newark, New Jersey": 425.27,
      "State Farm Arena, Atlanta, Georgia": 337.9,
      "Lucas Oil Stadium, Indianapolis, Indiana": 470.41,
      "Chase Center, San Francisco, California": 2383.49,
      "Alamodome, San Antonio, Texas": 1214.67
    }
  },
  {
    "team": "Michigan",
    "region": "South",
    "seed": 10,
    "elo": 1812.236,
    "conference": "Big Ten",
    "homeCourt": 74.46034,
    "distances": {
      "University of Dayton Arena, Dayton, Ohio": 177.25,
      "Amica Mutual Pavilion, Providence, Rhode Island": 634.49,
      "Rupp Arena, Lexington, Kentucky": 294.7,
      "Intrust Bank Arena, Wichita, Kansas": 786.46,
      "Ball Arena, Denver, Colorado": 1121.79,
      "Rocket Mortgage FieldHouse, Cleveland, Ohio": 119.23,
      "Fiserv Forum, Milwaukee, Wisconsin": 218.8,
      "PNC Arena, Raleigh, North Carolina": 522.07,
      "Climate Pledge Arena, Seattle, Washington": 1907.98,
      "Prudential Center, Newark, New Jersey": 507.89,
      "State Farm Arena, Atlanta, Georgia": 588.96,
      "Lucas Oil Stadium, Indianapolis, Indiana": 214.99,
      "Chase Center, San Francisco, California": 2055.1,
      "Alamodome, San Antonio, Texas": 1208.99
    }
  },
  {
    "team": "Oregon",
    "region": "Midwest",
    "seed": 11,
    "elo": 1810.116,
    "conference": "Big Ten",
    "homeCourt": 51.82573,
    "distances": {
      "University of Dayton Arena, Dayton, Ohio": 2007.59,
      "Amica Mutual Pavilion, Providence, Rhode Island": 2581.1,
      "Rupp Arena, Lexington, Kentucky": 2037.55,
      "Intrust Bank Arena, Wichita, Kansas": 1411.25,
      "Ball Arena, Denver, Colorado": 975.15,
      "Rocket Mortgage FieldHouse, Cleveland, Ohio": 2089.71,
      "Fiserv Forum, Milwaukee, Wisconsin": 1753.25,
      "PNC Arena, Raleigh, North Carolina": 2392.98,
      "Climate Pledge Arena, Seattle, Washington": 249.49,
      "Prudential Center, Newark, New Jersey": 2475.63,
      "State Farm Arena, Atlanta, Georgia": 2179.06,
      "Lucas Oil Stadium, Indianapolis, Indiana": 1909.51,
      "Chase Center, San Francisco, California": 434.58,
      "Alamodome, San Antonio, Texas": 1686.15
    }
  },
  {
    "team": "Missouri",
    "region": "East",
    "seed": 11,
    "elo": 1803.644,
    "conference": "SEC",
    "homeCourt": 85.52576,
    "distances": {
      "University of Dayton Arena, Dayton, Ohio": 438.85,
      "Amica Mutual Pavilion, Providence, Rhode Island": 1118.35,
      "Rupp Arena, Lexington, Kentucky": 428.56,
      "Intrust Bank Arena, Wichita, Kansas": 285.22,
      "Ball Arena, Denver, Colorado": 680.84,
      "Rocket Mortgage FieldHouse, Cleveland, Ohio": 589.45,
      "Fiserv Forum, Milwaukee, Wisconsin": 365.4,
      "PNC Arena, Raleigh, North Carolina": 778.64,
      "Climate Pledge Arena, Seattle, Washington": 1616.08,
      "Prudential Center, Newark, New Jersey": 971.99,
      "State Farm Arena, Atlanta, Georgia": 568.22,
      "Lucas Oil Stadium, Indianapolis, Indiana": 335.03,
      "Chase Center, San Francisco, California": 1627.16,
      "Alamodome, San Antonio, Texas": 744.24
    }
  },
  {
    "team": "Indiana",
    "region": "West",
    "seed": 11,
    "elo": 1792.548,
    "conference": "Big Ten",
    "homeCourt": 86.79526,
    "distances": {
      "University of Dayton Arena, Dayton, Ohio": 129.31,
      "Amica Mutual Pavilion, Providence, Rhode Island": 814.36,
      "Rupp Arena, Lexington, Kentucky": 133.71,
      "Intrust Bank Arena, Wichita, Kansas": 595.81,
      "Ball Arena, Denver, Colorado": 988.18,
      "Rocket Mortgage FieldHouse, Cleveland, Ohio": 300.48,
      "Fiserv Forum, Milwaukee, Wisconsin": 276.62,
      "PNC Arena, Raleigh, North Carolina": 486.93,
      "Climate Pledge Arena, Seattle, Washington": 1876.84,
      "Prudential Center, Newark, New Jersey": 663.23,
      "State Farm Arena, Atlanta, Georgia": 391.96,
      "Lucas Oil Stadium, Indianapolis, Indiana": 44.0,
      "Chase Center, San Francisco, California": 1935.16,
      "Alamodome, San Antonio, Texas": 958.35
    }
  },
  {
    "team": "San Diego St.",
    "region": "South",
    "seed": 11,
    "elo": 1790.632,
    "conference": "MWC",
    "homeCourt": 62.84991,
    "distances": {
      "University of Dayton Arena, Dayton, Ohio": 1885.88,
      "Amica Mutual Pavilion, Providence, Rhode Island": 2559.74,
      "Rupp Arena, Lexington, Kentucky": 1863.89,
      "Intrust Bank Arena, Wichita, Kansas": 1164.19,
      "Ball Arena, Denver, Colorado": 826.43,
      "Rocket Mortgage FieldHouse, Cleveland, Ohio": 2028.05,
      "Fiserv Forum, Milwaukee, Wisconsin": 1731.92,
      "PNC Arena, Raleigh, North Carolina": 2190.03,
      "Climate Pledge Arena, Seattle, Washington": 1061.07,
      "Prudential Center, Newark, New Jersey": 2417.78,
      "State Farm Arena, Atlanta, Georgia": 1885.07,
      "Lucas Oil Stadium, Indianapolis, Indiana": 1781.84,
      "Chase Center, San Francisco, California": 456.64,
      "Alamodome, San Antonio, Texas": 1124.78
    }
  },
  {
    "team": "Boise St.",
    "region": "Midwest",
    "seed": 12,
    "elo": 1775.204,
    "conference": "MWC",
    "homeCourt": 67.10416,
    "distances": {
      "University of Dayton Arena, Dayton, Ohio": 1666.81,
      "Amica Mutual Pavilion, Providence, Rhode Island": 2255.14,
      "Rupp Arena, Lexington, Kentucky": 1694.19,
      "Intrust Bank Arena, Wichita, Kansas": 1069.58,
      "Ball Arena, Denver, Colorado": 636.7,
      "Rocket Mortgage FieldHouse, Cleveland, Ohio": 1754.72,
      "Fiserv Forum, Milwaukee, Wisconsin": 1419.18,
      "PNC Arena, Raleigh, North Carolina": 2049.59,
      "Climate Pledge Arena, Seattle, Washington": 407.09,
      "Prudential Center, Newark, New Jersey": 2144.1,
      "State Farm Arena, Atlanta, Georgia": 1834.99,
      "Lucas Oil Stadium, Indianapolis, Indiana": 1567.76,
      "Chase Center, San Francisco, California": 517.04,
      "Alamodome, San Antonio, Texas": 1383.53
    }
  },
  {
    "team": "Mississippi St.",
    "region": "South",
    "seed": 12,
    "elo": 1771.446,
    "conference": "SEC",
    "homeCourt": 65.56918,
    "distances": {
      "University of Dayton Arena, Dayton, Ohio": 502.67,
      "Amica Mutual Pavilion, Providence, Rhode Island": 1111.52,
      "Rupp Arena, Lexington, Kentucky": 398.25,
      "Intrust Bank Arena, Wichita, Kansas": 560.66,
      "Ball Arena, Denver, Colorado": 997.02,
      "Rocket Mortgage FieldHouse, Cleveland, Ohio": 677.89,
      "Fiserv Forum, Milwaukee, Wisconsin": 662.63,
      "PNC Arena, Raleigh, North Carolina": 596.93,
      "Climate Pledge Arena, Seattle, Washington": 1995.5,
      "Prudential Center, Newark, New Jersey": 949.72,
      "State Farm Arena, Atlanta, Georgia": 255.6,
      "Lucas Oil Stadium, Indianapolis, Indiana": 458.35,
      "Chase Center, San Francisco, California": 1902.74,
      "Alamodome, San Antonio, Texas": 634.89
    }
  },
  {
    "team": "Liberty",
    "region": "East",
    "seed": 12,
    "elo": 1760.209,
    "conference": "CUSA",
    "homeCourt": 51.31514,
    "distances": {
      "University of Dayton Arena, Dayton, Ohio": 317.17,
      "Amica Mutual Pavilion, Providence, Rhode Island": 511.9,
      "Rupp Arena, Lexington, Kentucky": 296.81,
      "Intrust Bank Arena, Wichita, Kansas": 997.39,
      "Ball Arena, Denver, Colorado": 1404.73,
      "Rocket Mortgage FieldHouse, Cleveland, Ohio": 312.82,
      "Fiserv Forum, Milwaukee, Wisconsin": 604.64,
      "PNC Arena, Raleigh, North Carolina": 113.47,
      "Climate Pledge Arena, Seattle, Washington": 2282.93,
      "Prudential Center, Newark, New Jersey": 351.88,
      "State Farm Arena, Atlanta, Georgia": 388.59,
      "Lucas Oil Stadium, Indianapolis, Indiana": 412.98,
      "Chase Center, San Francisco, California": 2351.67,
      "Alamodome, San Antonio, Texas": 1242.74
    }
  },
  {
    "team": "Yale",
    "region": "West",
    "seed": 12,
    "elo": 1754.658,
    "conference": "Ivy",
    "homeCourt": 53.00887,
    "distances": {
      "University of Dayton Arena, Dayton, Ohio": 599.31,
      "Amica Mutual Pavilion, Providence, Rhode Island": 90.38,
      "Rupp Arena, Lexington, Kentucky": 651.99,
      "Intrust Bank Arena, Wichita, Kansas": 1320.15,
      "Ball Arena, Denver, Colorado": 1680.04,
      "Rocket Mortgage FieldHouse, Cleveland, Ohio": 452.28,
      "Fiserv Forum, Milwaukee, Wisconsin": 775.47,
      "PNC Arena, Raleigh, North Carolina": 487.57,
      "Climate Pledge Arena, Seattle, Washington": 2438.68,
      "Prudential Center, Newark, New Jersey": 71.55,
      "State Farm Arena, Atlanta, Georgia": 811.3,
      "Lucas Oil Stadium, Indianapolis, Indiana": 700.78,
      "Chase Center, San Francisco, California": 2615.02,
      "Alamodome, San Antonio, Texas": 1646.03
    }
  },
  {
    "team": "Wake Forest",
    "region": "Midwest",
    "seed": 13,
    "elo": 1754.622,
    "conference": "ACC",
    "homeCourt": 75.85943,
    "distances": {
      "University of Dayton Arena, Dayton, Ohio": 330.97,
      "Amica Mutual Pavilion, Providence, Rhode Island": 617.33,
      "Rupp Arena, Lexington, Kentucky": 270.95,
      "Intrust Bank Arena, Wichita, Kansas": 951.4,
      "Ball Arena, Denver, Colorado": 1371.51,
      "Rocket Mortgage FieldHouse, Cleveland, Ohio": 380.33,
      "Fiserv Forum, Milwaukee, Wisconsin": 629.84,
      "PNC Arena, Raleigh, North Carolina": 87.74,
      "Climate Pledge Arena, Seattle, Washington": 2280.66,
      "Prudential Center, Newark, New Jersey": 458.86,
      "State Farm Arena, Atlanta, Georgia": 285.69,
      "Lucas Oil Stadium, Indianapolis, Indiana": 410.05,
      "Chase Center, San Francisco, California": 2315.95,
      "Alamodome, San Antonio, Texas": 1154.88
    }
  },
  {
    "team": "High Point",
    "region": "West",
    "seed": 13,
    "elo": 1753.002,
    "conference": "Big South",
    "homeCourt": 64.58089,
    "distances": {
      "University of Dayton Arena, Dayton, Ohio": 347.16,
      "Amica Mutual Pavilion, Providence, Rhode Island": 614.37,
      "Rupp Arena, Lexington, Kentucky": 287.54,
      "Intrust Bank Arena, Wichita, Kansas": 966.54,
      "Ball Arena, Denver, Colorado": 1387.32,
      "Rocket Mortgage FieldHouse, Cleveland, Ohio": 392.86,
      "Fiserv Forum, Milwaukee, Wisconsin": 645.92,
      "PNC Arena, Raleigh, North Carolina": 72.77,
      "Climate Pledge Arena, Seattle, Washington": 2297.3,
      "Prudential Center, Newark, New Jersey": 456.99,
      "State Farm Arena, Atlanta, Georgia": 291.88,
      "Lucas Oil Stadium, Indianapolis, Indiana": 426.68,
      "Chase Center, San Francisco, California": 2331.53,
      "Alamodome, San Antonio, Texas": 1164.55
    }
  },
  {
    "team": "Dayton",
    "region": "East",
    "seed": 13,
    "elo": 1749.489,
    "conference": "A-10",
    "homeCourt": 89.27766,
    "distances": {
      "University of Dayton Arena, Dayton, Ohio": 1.67,
      "Amica Mutual Pavilion, Providence, Rhode Island": 684.18,
      "Rupp Arena, Lexington, Kentucky": 119.11,
      "Intrust Bank Arena, Wichita, Kansas": 723.66,
      "Ball Arena, Denver, Colorado": 1105.97,
      "Rocket Mortgage FieldHouse, Cleveland, Ohio": 178.01,
      "Fiserv Forum, Milwaukee, Wisconsin": 298.1,
      "PNC Arena, Raleigh, North Carolina": 404.89,
      "Climate Pledge Arena, Seattle, Washington": 1965.37,
      "Prudential Center, Newark, New Jersey": 533.74,
      "State Farm Arena, Atlanta, Georgia": 414.0,
      "Lucas Oil Stadium, Indianapolis, Indiana": 105.01,
      "Chase Center, San Francisco, California": 2051.74,
      "Alamodome, San Antonio, Texas": 1079.85
    }
  },
  {
    "team": "Villanova",
    "region": "South",
    "seed": 13,
    "elo": 1746.929,
    "conference": "Big East",
    "homeCourt": 61.80666,
    "distances": {
      "University of Dayton Arena, Dayton, Ohio": 471.05,
      "Amica Mutual Pavilion, Providence, Rhode Island": 239.49,
      "Rupp Arena, Lexington, Kentucky": 511.22,
      "Intrust Bank Arena, Wichita, Kansas": 1193.94,
      "Ball Arena, Denver, Colorado": 1569.32,
      "Rocket Mortgage FieldHouse, Cleveland, Ohio": 347.77,
      "Fiserv Forum, Milwaukee, Wisconsin": 683.49,
      "PNC Arena, Raleigh, North Carolina": 345.4,
      "Climate Pledge Arena, Seattle, Washington": 2369.13,
      "Prudential Center, Newark, New Jersey": 78.28,
      "State Farm Arena, Atlanta, Georgia": 661.89,
      "Lucas Oil Stadium, Indianapolis, Indiana": 575.04,
      "Chase Center, San Francisco, California": 2511.0,
      "Alamodome, San Antonio, Texas": 1499.96
    }
  },
  {
    "team": "UC Irvine",
    "region": "South",
    "seed": 14,
    "elo": 1744.086,
    "conference": "Big West",
    "homeCourt": 50.66346,
    "distances": {
      "University of Dayton Arena, Dayton, Ohio": 1902.97,
      "Amica Mutual Pavilion, Providence, Rhode Island": 2572.13,
      "Rupp Arena, Lexington, Kentucky": 1885.57,
      "Intrust Bank Arena, Wichita, Kansas": 1184.34,
      "Ball Arena, Denver, Colorado": 826.43,
      "Rocket Mortgage FieldHouse, Cleveland, Ohio": 2040.8,
      "Fiserv Forum, Milwaukee, Wisconsin": 1738.39,
      "PNC Arena, Raleigh, North Carolina": 2216.61,
      "Climate Pledge Arena, Seattle, Washington": 992.87,
      "Prudential Center, Newark, New Jersey": 2432.67,
      "State Farm Arena, Atlanta, Georgia": 1917.97,
      "Lucas Oil Stadium, Indianapolis, Indiana": 1798.58,
      "Chase Center, San Francisco, California": 382.33,
      "Alamodome, San Antonio, Texas": 1177.09
    }
  },
  {
    "team": "Northwestern",
    "region": "West",
    "seed": 14,
    "elo": 1742.7,
    "conference": "Big Ten",
    "homeCourt": 25.67289,
    "distances": {
      "University of Dayton Arena, Dayton, Ohio": 242.34,
      "Amica Mutual Pavilion, Providence, Rhode Island": 836.62,
      "Rupp Arena, Lexington, Kentucky": 323.52,
      "Intrust Bank Arena, Wichita, Kansas": 594.89,
      "Ball Arena, Denver, Colorado": 919.65,
      "Rocket Mortgage FieldHouse, Cleveland, Ohio": 311.61,
      "Fiserv Forum, Milwaukee, Wisconsin": 69.39,
      "PNC Arena, Raleigh, North Carolina": 646.42,
      "Climate Pledge Arena, Seattle, Washington": 1731.16,
      "Prudential Center, Newark, New Jersey": 706.91,
      "State Farm Arena, Atlanta, Georgia": 599.59,
      "Lucas Oil Stadium, Indianapolis, Indiana": 177.13,
      "Chase Center, San Francisco, California": 1854.79,
      "Alamodome, San Antonio, Texas": 1060.13
    }
  },
  {
    "team": "Utah St.",
    "region": "East",
    "seed": 14,
    "elo": 1739.857,
    "conference": "MWC",
    "homeCourt": 94.38869,
    "distances": {
      "University of Dayton Arena, Dayton, Ohio": 1449.35,
      "Amica Mutual Pavilion, Providence, Rhode Island": 2066.57,
      "Rupp Arena, Lexington, Kentucky": 1466.91,
      "Intrust Bank Arena, Wichita, Kansas": 819.55,
      "Ball Arena, Denver, Colorado": 382.61,
      "Rocket Mortgage FieldHouse, Cleveland, Ohio": 1551.76,
      "Fiserv Forum, Milwaukee, Wisconsin": 1221.35,
      "PNC Arena, Raleigh, North Carolina": 1821.06,
      "Climate Pledge Arena, Seattle, Washington": 657.85,
      "Prudential Center, Newark, New Jersey": 1945.94,
      "State Farm Arena, Atlanta, Georgia": 1590.78,
      "Lucas Oil Stadium, Indianapolis, Indiana": 1347.61,
      "Chase Center, San Francisco, California": 626.18,
      "Alamodome, San Antonio, Texas": 1131.56
    }
  },
  {
    "team": "Ohio St.",
    "region": "Midwest",
    "seed": 14,
    "elo": 1738.357,
    "conference": "Big Ten",
    "homeCourt": 71.84576,
    "distances": {
      "University of Dayton Arena, Dayton, Ohio": 64.99,
      "Amica Mutual Pavilion, Providence, Rhode Island": 620.07,
      "Rupp Arena, Lexington, Kentucky": 156.51,
      "Intrust Bank Arena, Wichita, Kansas": 787.12,
      "Ball Arena, Denver, Colorado": 1165.48,
      "Rocket Mortgage FieldHouse, Cleveland, Ohio": 124.62,
      "Fiserv Forum, Milwaukee, Wisconsin": 328.96,
      "PNC Arena, Raleigh, North Carolina": 373.24,
      "Climate Pledge Arena, Seattle, Washington": 2011.54,
      "Prudential Center, Newark, New Jersey": 469.94,
      "State Farm Arena, Atlanta, Georgia": 437.46,
      "Lucas Oil Stadium, Indianapolis, Indiana": 167.5,
      "Chase Center, San Francisco, California": 2110.31,
      "Alamodome, San Antonio, Texas": 1139.88
    }
  },
  {
    "team": "Oklahoma",
    "region": "East",
    "seed": 15,
    "elo": 1736.698,
    "conference": "SEC",
    "homeCourt": 86.2571,
    "distances": {
      "University of Dayton Arena, Dayton, Ohio": 790.39,
      "Amica Mutual Pavilion, Providence, Rhode Island": 1475.01,
      "Rupp Arena, Lexington, Kentucky": 744.18,
      "Intrust Bank Arena, Wichita, Kansas": 169.78,
      "Ball Arena, Denver, Colorado": 519.68,
      "Rocket Mortgage FieldHouse, Cleveland, Ohio": 956.62,
      "Fiserv Forum, Milwaukee, Wisconsin": 742.59,
      "PNC Arena, Raleigh, North Carolina": 1054.22,
      "Climate Pledge Arena, Seattle, Washington": 1540.63,
      "Prudential Center, Newark, New Jersey": 1321.4,
      "State Farm Arena, Atlanta, Georgia": 750.67,
      "Lucas Oil Stadium, Indianapolis, Indiana": 693.39,
      "Chase Center, San Francisco, California": 1395.77,
      "Alamodome, San Antonio, Texas": 404.63
    }
  },
  {
    "team": "SMU",
    "region": "Midwest",
    "seed": 15,
    "elo": 1735.086,
    "conference": "ACC",
    "homeCourt": 53.83228,
    "distances": {
      "University of Dayton Arena, Dayton, Ohio": 846.71,
      "Amica Mutual Pavilion, Providence, Rhode Island": 1520.39,
      "Rupp Arena, Lexington, Kentucky": 779.3,
      "Intrust Bank Arena, Wichita, Kansas": 335.22,
      "Ball Arena, Denver, Colorado": 660.92,
      "Rocket Mortgage FieldHouse, Cleveland, Ohio": 1022.21,
      "Fiserv Forum, Milwaukee, Wisconsin": 853.04,
      "PNC Arena, Raleigh, North Carolina": 1051.15,
      "Climate Pledge Arena, Seattle, Washington": 1680.42,
      "Prudential Center, Newark, New Jersey": 1361.87,
      "State Farm Arena, Atlanta, Georgia": 719.09,
      "Lucas Oil Stadium, Indianapolis, Indiana": 759.72,
      "Chase Center, San Francisco, California": 1481.31,
      "Alamodome, San Antonio, Texas": 256.49
    }
  },
  {
    "team": "Santa Clara",
    "region": "West",
    "seed": 15,
    "elo": 1731.439,
    "conference": "WCC",
    "homeCourt": 26.22042,
    "distances": {
      "University of Dayton Arena, Dayton, Ohio": 2036.69,
      "Amica Mutual Pavilion, Providence, Rhode Island": 2676.21,
      "Rupp Arena, Lexington, Kentucky": 2038.81,
      "Intrust Bank Arena, Wichita, Kansas": 1348.87,
      "Ball Arena, Denver, Colorado": 931.24,
      "Rocket Mortgage FieldHouse, Cleveland, Ohio": 2153.63,
      "Fiserv Forum, Milwaukee, Wisconsin": 1829.85,
      "PNC Arena, Raleigh, North Carolina": 2385.56,
      "Climate Pledge Arena, Seattle, Washington": 709.01,
      "Prudential Center, Newark, New Jersey": 2549.32,
      "State Farm Arena, Atlanta, Georgia": 2116.5,
      "Lucas Oil Stadium, Indianapolis, Indiana": 1932.71,
      "Chase Center, San Francisco, California": 37.11,
      "Alamodome, San Antonio, Texas": 1458.34
    }
  },
  {
    "team": "San Francisco",
    "region": "South",
    "seed": 15,
    "elo": 1728.765,
    "conference": "WCC",
    "homeCourt": 50.82576,
    "distances": {
      "University of Dayton Arena, Dayton, Ohio": 2053.02,
      "Amica Mutual Pavilion, Providence, Rhode Island": 2688.43,
      "Rupp Arena, Lexington, Kentucky": 2057.22,
      "Intrust Bank Arena, Wichita, Kansas": 1370.02,
      "Ball Arena, Denver, Colorado": 948.55,
      "Rocket Mortgage FieldHouse, Cleveland, Ohio": 2167.5,
      "Fiserv Forum, Milwaukee, Wisconsin": 1842.02,
      "PNC Arena, Raleigh, North Carolina": 2405.18,
      "Climate Pledge Arena, Seattle, Washington": 679.41,
      "Prudential Center, Newark, New Jersey": 2563.06,
      "State Farm Arena, Atlanta, Georgia": 2139.6,
      "Lucas Oil Stadium, Indianapolis, Indiana": 1949.26,
      "Chase Center, San Francisco, California": 1.91,
      "Alamodome, San Antonio, Texas": 1490.68
    }
  },
  {
    "team": "George Mason",
    "region": "East",
    "seed": 16,
    "elo": 1725.851,
    "conference": "A-10",
    "homeCourt": 59.43953,
    "distances": {
      "University of Dayton Arena, Dayton, Ohio": 373.29,
      "Amica Mutual Pavilion, Providence, Rhode Island": 373.94,
      "Rupp Arena, Lexington, Kentucky": 392.68,
      "Intrust Bank Arena, Wichita, Kansas": 1088.42,
      "Ball Arena, Denver, Colorado": 1478.99,
      "Rocket Mortgage FieldHouse, Cleveland, Ohio": 294.63,
      "Fiserv Forum, Milwaukee, Wisconsin": 624.73,
      "PNC Arena, Raleigh, North Carolina": 222.82,
      "Climate Pledge Arena, Seattle, Washington": 2316.93,
      "Prudential Center, Newark, New Jersey": 213.05,
      "State Farm Arena, Atlanta, Georgia": 527.13,
      "Lucas Oil Stadium, Indianapolis, Indiana": 477.47,
      "Chase Center, San Francisco, California": 2424.76,
      "Alamodome, San Antonio, Texas": 1370.33
    }
  },
  {
    "team": "Penn St.",
    "region": "South",
    "seed": 16,
    "elo": 1718.627,
    "conference": "Big Ten",
    "homeCourt": 66.05668,
    "distances": {
      "University of Dayton Arena, Dayton, Ohio": 343.19,
      "Amica Mutual Pavilion, Providence, Rhode Island": 342.21,
      "Rupp Arena, Lexington, Kentucky": 402.98,
      "Intrust Bank Arena, Wichita, Kansas": 1064.31,
      "Ball Arena, Denver, Colorado": 1431.0,
      "Rocket Mortgage FieldHouse, Cleveland, Ohio": 205.55,
      "Fiserv Forum, Milwaukee, Wisconsin": 540.8,
      "PNC Arena, Raleigh, North Carolina": 348.0,
      "Climate Pledge Arena, Seattle, Washington": 2227.28,
      "Prudential Center, Newark, New Jersey": 193.36,
      "State Farm Arena, Atlanta, Georgia": 604.52,
      "Lucas Oil Stadium, Indianapolis, Indiana": 444.7,
      "Chase Center, San Francisco, California": 2370.85,
      "Alamodome, San Antonio, Texas": 1401.7
    }
  },
  {
    "team": "Rutgers",
    "region": "West",
    "seed": 16,
    "elo": 1718.259,
    "conference": "Big Ten",
    "homeCourt": 46.59946,
    "distances": {
      "University of Dayton Arena, Dayton, Ohio": 518.17,
      "Amica Mutual Pavilion, Providence, Rhode Island": 182.52,
      "Rupp Arena, Lexington, Kentucky": 564.1,
      "Intrust Bank Arena, Wichita, Kansas": 1241.0,
      "Ball Arena, Denver, Colorado": 1610.23,
      "Rocket Mortgage FieldHouse, Cleveland, Ohio": 383.46,
      "Fiserv Forum, Milwaukee, Wisconsin": 715.56,
      "PNC Arena, Raleigh, North Carolina": 399.38,
      "Climate Pledge Arena, Seattle, Washington": 2394.05,
      "Prudential Center, Newark, New Jersey": 21.32,
      "State Farm Arena, Atlanta, Georgia": 718.99,
      "Lucas Oil Stadium, Indianapolis, Indiana": 621.28,
      "Chase Center, San Francisco, California": 2549.55,
      "Alamodome, San Antonio, Texas": 1555.45
    }
  },
  {
    "team": "North Texas",
    "region": "Midwest",
    "seed": 16,
    "elo": 1714.791,
    "conference": "AAC",
    "homeCourt": 39.88673,
    "distances": {
      "University of Dayton Arena, Dayton, Ohio": 849.34,
      "Amica Mutual Pavilion, Providence, Rhode Island": 1526.22,
      "Rupp Arena, Lexington, Kentucky": 785.68,
      "Intrust Bank Arena, Wichita, Kansas": 310.38,
      "Ball Arena, Denver, Colorado": 629.42,
      "Rocket Mortgage FieldHouse, Cleveland, Ohio": 1023.47,
      "Fiserv Forum, Milwaukee, Wisconsin": 844.53,
      "PNC Arena, Raleigh, North Carolina": 1064.95,
      "Climate Pledge Arena, Seattle, Washington": 1648.99,
      "Prudential Center, Newark, New Jersey": 1368.45,
      "State Farm Arena, Atlanta, Georgia": 736.73,
      "Lucas Oil Stadium, Indianapolis, Indiana": 760.12,
      "Chase Center, San Francisco, California": 1453.59,
      "Alamodome, San Antonio, Texas": 271.31
    }
  }
]